{"stats":{"minecraft:picked_up":{"minecraft:mutton":2,"minecraft:wheat_seeds":1},"minecraft:mined":{"minecraft:grass":4},"minecraft:custom":{"minecraft:jump":8,"minecraft:time_since_rest":10803,"minecraft:damage_dealt":79,"minecraft:play_one_minute":10803,"minecraft:leave_game":3,"minecraft:sprint_one_cm":1168,"minecraft:time_since_death":10803,"minecraft:walk_on_water_one_cm":1285,"minecraft:walk_one_cm":1880,"minecraft:walk_under_water_one_cm":192,"minecraft:mob_kills":1,"minecraft:fly_one_cm":1365},"minecraft:killed":{"minecraft:sheep":1}},"DataVersion":1631}